setup.py
html_objects/__init__.py
html_objects/components.py
html_objects/google.py
html_objects/tests/__init__.py
html_objects/tests/test_components.py
html_objects/tests/test_google.py
python_html_objects.egg-info/PKG-INFO
python_html_objects.egg-info/SOURCES.txt
python_html_objects.egg-info/dependency_links.txt
python_html_objects.egg-info/top_level.txt