Metadata-Version: 1.0
Name: python-html-objects
Version: 0.1.0
Summary: Python library that contains objects that represents HTML tags.
Home-page: https://bitbucket.org/paulocheque/python-html-objects
Author: paulocheque
Author-email: paulocheque@gmail.com
License: MIT
Keywords: python html objects
Platform: UNKNOWN
